LICENSE
README.md
setup.py
src/pyvoyis/__init__.py
src/pyvoyis/api.py
src/pyvoyis/cli.py
src/pyvoyis/commander.py
src/pyvoyis/configuration.py
src/pyvoyis/messages.py
src/pyvoyis/state_machine.py
src/pyvoyis.egg-info/PKG-INFO
src/pyvoyis.egg-info/SOURCES.txt
src/pyvoyis.egg-info/dependency_links.txt
src/pyvoyis.egg-info/entry_points.txt
src/pyvoyis.egg-info/requires.txt
src/pyvoyis.egg-info/top_level.txt
src/pyvoyis/api500/__init__.py
src/pyvoyis/api500/client.py
src/pyvoyis/api500/command.py
src/pyvoyis/api500/defs.py