Metadata-Version: 2.1
Name: pyvoyis
Version: 1.0.4
Summary: Voyis Recon LS python driver
Home-page: https://github.com/miquelmassot/pyvoyis
Author: Miquel Massot
Author-email: miquel.massot@gmail.com
Maintainer: Miquel Massot
Maintainer-email: miquel.massot@gmail.com
License: GPLv3
Project-URL: Bug Reports, https://github.com/miquelmassot/pyvoyis/issues
Project-URL: Source, https://github.com/miquelmassot/pyvoyis
Classifier: Development Status :: 4 - Beta
Classifier: Intended Audience :: Developers
Classifier: Intended Audience :: Science/Research
Classifier: License :: OSI Approved :: GNU General Public License v3 (GPLv3)
Classifier: Programming Language :: Python :: 3
Classifier: Topic :: Software Development
Classifier: Topic :: Software Development :: Libraries
Classifier: Topic :: Software Development :: Libraries :: Python Modules
Classifier: Topic :: System :: Hardware :: Hardware Drivers
License-File: LICENSE
